miniProject/alarm_module.v
`timescale 1ns/1ps
module alarm_module(
    input  wire [4:0] cur_hour,    
    input  wire [5:0] cur_min,     
    input  wire [5:0] cur_sec,     
    input  wire [4:0] alarm_hour,
    input  wire [5:0] alarm_min,
    input  wire [5:0] alarm_sec,
    input  wire alarm_en,          
    input  wire clk,               
    input  wire reset_n,           
    output reg  alarm_out          
);

    wire match = alarm_en &&
                 (cur_hour == alarm_hour) &&
                 (cur_min  == alarm_min)  &&
                 (cur_sec  == alarm_sec);

    always @(posedge clk or negedge reset_n) begin
        if (!reset_n)
            alarm_out <= 1'b0;
        else if (match)
            alarm_out <= 1'b1;
        else
            alarm_out <= alarm_out; 
    end

endmodule

miniProject/hour_counter.v
`timescale 1ns/1ps
module hour_counter(
    input  wire hour_tick,   
    input  wire reset_n,
    output reg  [4:0] hour   
);
    always @(posedge hour_tick or negedge reset_n) begin
        if (!reset_n) begin
            hour <= 5'd0;
        end else begin
            if (hour == 5'd23)
                hour <= 5'd0;
            else
                hour <= hour + 5'd1;
        end
    end
endmodule

miniProject/minute_counter.v
`timescale 1ns/1ps
module minute_counter(
    input  wire minute_tick, 
    input  wire reset_n,
    output reg  [5:0] min,   
    output reg  hour_tick    
);
    always @(posedge minute_tick or negedge reset_n) begin
        if (!reset_n) begin
            min <= 6'd0;
            hour_tick <= 1'b0;
        end else begin
            if (min == 6'd59) begin
                min <= 6'd0;
                hour_tick <= 1'b1;
            end else begin
                min <= min + 6'd1;
                hour_tick <= 1'b0;
            end
        end
    end
endmodule

miniProject/second_counter.v
`timescale 1ns/1ps
module second_counter(
    input  wire tick,       
    input  wire reset_n,    
    output reg  [5:0] sec,  
    output reg  minute_tick 
);
    always @(posedge tick or negedge reset_n) begin
        if (!reset_n) begin
            sec <= 6'd0;
            minute_tick <= 1'b0;
        end else begin
            if (sec == 6'd59) begin
                sec <= 6'd0;
                minute_tick <= 1'b1;
            end else begin
                sec <= sec + 6'd1;
                minute_tick <= 1'b0;
            end
        end
    end
endmodule

miniProject/digital_clock.v
`timescale 1ns/1ps
module digital_clock_top(
    input  wire tick,           
    input  wire reset_n,        
    input  wire [4:0] alarm_hour,
    input  wire [5:0] alarm_min,
    input  wire [5:0] alarm_sec,
    input  wire alarm_en,
    input  wire alarm_reset_n,
    output wire [4:0] hour,
    output wire [5:0] min,
    output wire [5:0] sec,
    output wire alarm_out
);

    wire minute_tick;
    wire hour_tick;

    second_counter sec_cnt (
        .tick(tick),
        .reset_n(reset_n),
        .sec(sec),
        .minute_tick(minute_tick)
    );

    minute_counter min_cnt (
        .minute_tick(minute_tick),
        .reset_n(reset_n),
        .min(min),
        .hour_tick(hour_tick)
    );

    hour_counter hr_cnt (
        .hour_tick(hour_tick),
        .reset_n(reset_n),
        .hour(hour)
    );

    alarm_module alarm (
        .cur_hour(hour),
        .cur_min(min),
        .cur_sec(sec),
        .alarm_hour(alarm_hour),
        .alarm_min(alarm_min),
        .alarm_sec(alarm_sec),
        .alarm_en(alarm_en),
        .clk(tick),              
        .reset_n(alarm_reset_n), 
        .alarm_out(alarm_out)
    );
endmodule

miniProject/tb_digital_clock.v
`timescale 1ns/1ps
module tb_digital_clock;
    reg tick;
    reg reset_n;
    reg alarm_en;
    reg alarm_reset_n;
    reg [4:0] alarm_hour;
    reg [5:0] alarm_min;
    reg [5:0] alarm_sec;

    wire [4:0] hour;
    wire [5:0] min;
    wire [5:0] sec;
    wire alarm_out;

    digital_clock_top dut (
        .tick(tick),
        .reset_n(reset_n),
        .alarm_hour(alarm_hour),
        .alarm_min(alarm_min),
        .alarm_sec(alarm_sec),
        .alarm_en(alarm_en),
        .alarm_reset_n(alarm_reset_n),
        .hour(hour),
        .min(min),
        .sec(sec),
        .alarm_out(alarm_out)
    );

    initial begin
        $dumpfile("clock_tb.vcd");
        $dumpvars(0, tb_digital_clock);
    end

    initial begin
        tick = 0;
        forever begin
            #5 tick = ~tick;
        end
    end

    initial begin
        reset_n = 0;
        alarm_reset_n = 1;
        alarm_en = 0;
        alarm_hour = 5'd0;
        alarm_min  = 6'd0;
        alarm_sec  = 6'd20;
        #30; 
        reset_n = 1; 

        #200; 
        alarm_en = 1;

        #400;

        $display("Time: %0t ns, Clock = %0d:%0d:%0d, alarm_out=%b", $time, hour, min, sec, alarm_out);

        #20;
        alarm_reset_n = 0;
        #10;
        alarm_reset_n = 1;
        alarm_en = 0;

        #200;
        $display("Simulation finished at %0t ns", $time);
        $finish;
    end

    always @(posedge tick) begin
        $display("T=%0t ns : %0d:%0d:%0d alarm=%b", $time, hour, min, sec, alarm_out);
    end

endmodule

miniProject/clock_tb.vcd
$date
	Sun Nov  9 13:47:37 2025
$end
$version
	Icarus Verilog
$end
$timescale
	1ps
$end
$scope module tb_digital_clock $end
$var wire 6 ! sec [5:0] $end
$var wire 6 " min [5:0] $end
$var wire 5 # hour [4:0] $end
$var wire 1 $ alarm_out $end
$var reg 1 % alarm_en $end
$var reg 5 & alarm_hour [4:0] $end
$var reg 6 ' alarm_min [5:0] $end
$var reg 1 ( alarm_reset_n $end
$var reg 6 ) alarm_sec [5:0] $end
$var reg 1 * reset_n $end
$var reg 1 + tick $end
$scope module dut $end
$var wire 1 % alarm_en $end
$var wire 5 , alarm_hour [4:0] $end
$var wire 6 - alarm_min [5:0] $end
$var wire 1 ( alarm_reset_n $end
$var wire 6 . alarm_sec [5:0] $end
$var wire 1 * reset_n $end
$var wire 1 + tick $end
$var wire 6 / sec [5:0] $end
$var wire 1 0 minute_tick $end
$var wire 6 1 min [5:0] $end
$var wire 1 2 hour_tick $end
$var wire 5 3 hour [4:0] $end
$var wire 1 $ alarm_out $end
$scope module alarm $end
$var wire 1 % alarm_en $end
$var wire 5 4 alarm_hour [4:0] $end
$var wire 6 5 alarm_min [5:0] $end
$var wire 6 6 alarm_sec [5:0] $end
$var wire 1 + clk $end
$var wire 1 7 match $end
$var wire 1 ( reset_n $end
$var wire 6 8 cur_sec [5:0] $end
$var wire 6 9 cur_min [5:0] $end
$var wire 5 : cur_hour [4:0] $end
$var reg 1 $ alarm_out $end
$upscope $end
$scope module hr_cnt $end
$var wire 1 * reset_n $end
$var wire 1 2 hour_tick $end
$var reg 5 ; hour [4:0] $end
$upscope $end
$scope module min_cnt $end
$var wire 1 * reset_n $end
$var wire 1 0 minute_tick $end
$var reg 1 2 hour_tick $end
$var reg 6 < min [5:0] $end
$upscope $end
$scope module sec_cnt $end
$var wire 1 * reset_n $end
$var wire 1 + tick $end
$var reg 1 0 minute_tick $end
$var reg 6 = sec [5:0] $end
$upscope $end
$upscope $end
$upscope $end
$enddefinitions $end
$comment Show the parameter values. $end
$dumpall
$end
#0
$dumpvars
b0 =
b0 <
b0 ;
b0 :
b0 9
b0 8
07
b10100 6
b0 5
b0 4
b0 3
02
b0 1
00
b0 /
b10100 .
b0 -
b0 ,
0+
0*
b10100 )
1(
b0 '
b0 &
0%
x$
b0 #
b0 "
b0 !
$end
#5000
1+
#10000
0+
#15000
1+
#20000
0+
#25000
1+
#30000
0+
1*
#35000
b1 !
b1 /
b1 8
b1 =
1+
#40000
0+
#45000
b10 !
b10 /
b10 8
b10 =
1+
#50000
0+
#55000
b11 !
b11 /
b11 8
b11 =
1+
#60000
0+
#65000
b100 !
b100 /
b100 8
b100 =
1+
#70000
0+
#75000
b101 !
b101 /
b101 8
b101 =
1+
#80000
0+
#85000
b110 !
b110 /
b110 8
b110 =
1+
#90000
0+
#95000
b111 !
b111 /
b111 8
b111 =
1+
#100000
0+
#105000
b1000 !
b1000 /
b1000 8
b1000 =
1+
#110000
0+
#115000
b1001 !
b1001 /
b1001 8
b1001 =
1+
#120000
0+
#125000
b1010 !
b1010 /
b1010 8
b1010 =
1+
#130000
0+
#135000
b1011 !
b1011 /
b1011 8
b1011 =
1+
#140000
0+
#145000
b1100 !
b1100 /
b1100 8
b1100 =
1+
#150000
0+
#155000
b1101 !
b1101 /
b1101 8
b1101 =
1+
#160000
0+
#165000
b1110 !
b1110 /
b1110 8
b1110 =
1+
#170000
0+
#175000
b1111 !
b1111 /
b1111 8
b1111 =
1+
#180000
0+
#185000
b10000 !
b10000 /
b10000 8
b10000 =
1+
#190000
0+
#195000
b10001 !
b10001 /
b10001 8
b10001 =
1+
#200000
0+
#205000
b10010 !
b10010 /
b10010 8
b10010 =
1+
#210000
0+
#215000
b10011 !
b10011 /
b10011 8
b10011 =
1+
#220000
0+
#225000
b10100 !
b10100 /
b10100 8
b10100 =
1+
#230000
17
0+
1%
#235000
07
1$
b10101 !
b10101 /
b10101 8
b10101 =
1+
#240000
0+
#245000
b10110 !
b10110 /
b10110 8
b10110 =
1+
#250000
0+
#255000
b10111 !
b10111 /
b10111 8
b10111 =
1+
#260000
0+
#265000
b11000 !
b11000 /
b11000 8
b11000 =
1+
#270000
0+
#275000
b11001 !
b11001 /
b11001 8
b11001 =
1+
#280000
0+
#285000
b11010 !
b11010 /
b11010 8
b11010 =
1+
#290000
0+
#295000
b11011 !
b11011 /
b11011 8
b11011 =
1+
#300000
0+
#305000
b11100 !
b11100 /
b11100 8
b11100 =
1+
#310000
0+
#315000
b11101 !
b11101 /
b11101 8
b11101 =
1+
#320000
0+
#325000
b11110 !
b11110 /
b11110 8
b11110 =
1+
#330000
0+
#335000
b11111 !
b11111 /
b11111 8
b11111 =
1+
#340000
0+
#345000
b100000 !
b100000 /
b100000 8
b100000 =
1+
#350000
0+
#355000
b100001 !
b100001 /
b100001 8
b100001 =
1+
#360000
0+
#365000
b100010 !
b100010 /
b100010 8
b100010 =
1+
#370000
0+
#375000
b100011 !
b100011 /
b100011 8
b100011 =
1+
#380000
0+
#385000
b100100 !
b100100 /
b100100 8
b100100 =
1+
#390000
0+
#395000
b100101 !
b100101 /
b100101 8
b100101 =
1+
#400000
0+
#405000
b100110 !
b100110 /
b100110 8
b100110 =
1+
#410000
0+
#415000
b100111 !
b100111 /
b100111 8
b100111 =
1+
#420000
0+
#425000
b101000 !
b101000 /
b101000 8
b101000 =
1+
#430000
0+
#435000
b101001 !
b101001 /
b101001 8
b101001 =
1+
#440000
0+
#445000
b101010 !
b101010 /
b101010 8
b101010 =
1+
#450000
0+
#455000
b101011 !
b101011 /
b101011 8
b101011 =
1+
#460000
0+
#465000
b101100 !
b101100 /
b101100 8
b101100 =
1+
#470000
0+
#475000
b101101 !
b101101 /
b101101 8
b101101 =
1+
#480000
0+
#485000
b101110 !
b101110 /
b101110 8
b101110 =
1+
#490000
0+
#495000
b101111 !
b101111 /
b101111 8
b101111 =
1+
#500000
0+
#505000
b110000 !
b110000 /
b110000 8
b110000 =
1+
#510000
0+
#515000
b110001 !
b110001 /
b110001 8
b110001 =
1+
#520000
0+
#525000
b110010 !
b110010 /
b110010 8
b110010 =
1+
#530000
0+
#535000
b110011 !
b110011 /
b110011 8
b110011 =
1+
#540000
0+
#545000
b110100 !
b110100 /
b110100 8
b110100 =
1+
#550000
0+
#555000
b110101 !
b110101 /
b110101 8
b110101 =
1+
#560000
0+
#565000
b110110 !
b110110 /
b110110 8
b110110 =
1+
#570000
0+
#575000
b110111 !
b110111 /
b110111 8
b110111 =
1+
#580000
0+
#585000
b111000 !
b111000 /
b111000 8
b111000 =
1+
#590000
0+
#595000
b111001 !
b111001 /
b111001 8
b111001 =
1+
#600000
0+
#605000
b111010 !
b111010 /
b111010 8
b111010 =
1+
#610000
0+
#615000
b111011 !
b111011 /
b111011 8
b111011 =
1+
#620000
0+
#625000
b1 "
b1 1
b1 9
b1 <
10
b0 !
b0 /
b0 8
b0 =
1+
#630000
0+
#635000
00
b1 !
b1 /
b1 8
b1 =
1+
#640000
0+
#645000
b10 !
b10 /
b10 8
b10 =
1+
#650000
0$
0+
0(
#655000
b11 !
b11 /
b11 8
b11 =
1+
#660000
0+
0%
1(
#665000
b100 !
b100 /
b100 8
b100 =
1+
#670000
0+
#675000
b101 !
b101 /
b101 8
b101 =
1+
#680000
0+
#685000
b110 !
b110 /
b110 8
b110 =
1+
#690000
0+
#695000
b111 !
b111 /
b111 8
b111 =
1+
#700000
0+
#705000
b1000 !
b1000 /
b1000 8
b1000 =
1+
#710000
0+
#715000
b1001 !
b1001 /
b1001 8
b1001 =
1+
#720000
0+
#725000
b1010 !
b1010 /
b1010 8
b1010 =
1+
#730000
0+
#735000
b1011 !
b1011 /
b1011 8
b1011 =
1+
#740000
0+
#745000
b1100 !
b1100 /
b1100 8
b1100 =
1+
#750000
0+
#755000
b1101 !
b1101 /
b1101 8
b1101 =
1+
#760000
0+
#765000
b1110 !
b1110 /
b1110 8
b1110 =
1+
#770000
0+
#775000
b1111 !
b1111 /
b1111 8
b1111 =
1+
#780000
0+
#785000
b10000 !
b10000 /
b10000 8
b10000 =
1+
#790000
0+
#795000
b10001 !
b10001 /
b10001 8
b10001 =
1+
#800000
0+
#805000
b10010 !
b10010 /
b10010 8
b10010 =
1+
#810000
0+
#815000
b10011 !
b10011 /
b10011 8
b10011 =
1+
#820000
0+
#825000
b10100 !
b10100 /
b10100 8
b10100 =
1+
#830000
0+
#835000
b10101 !
b10101 /
b10101 8
b10101 =
1+
#840000
0+
#845000
b10110 !
b10110 /
b10110 8
b10110 =
1+
#850000
0+
#855000
b10111 !
b10111 /
b10111 8
b10111 =
1+
